Metadata-Version: 2.1
Name: grape-grape
Version: 1.0.3
Summary: grape_grape
Home-page: UNKNOWN
Author: putao
Author-email: putaoisapig@163.com
License: UNKNOWN
Platform: UNKNOWN
Requires-Python: >=3.6
